perfect_eval/__init__.py
perfect_eval/__version__.py
perfect_eval/eval.py
perfect_eval-0.0.10.dist-info/LICENSE
perfect_eval-0.0.10.dist-info/METADATA
perfect_eval-0.0.10.dist-info/WHEEL
perfect_eval-0.0.10.dist-info/top_level.txt
perfect_eval-0.0.10.dist-info/RECORD
