Metadata-Version: 2.1
Name: perfect-eval
Version: 0.0.10
Summary: Safe execute expr code.
Home-page: https://github.com/holbos-deng/perfect-eval
Author: Holbos Deng
Author-email: 2292861292@qq.com
License: MIT
Classifier: License :: OSI Approved :: MIT License
Classifier: Programming Language :: Python
Classifier: Programming Language :: Python :: 3
Classifier: Programming Language :: Python :: 3.7
Classifier: Programming Language :: Python :: 3.8
Classifier: Programming Language :: Python :: 3.9
Classifier: Programming Language :: Python :: 3.10
Classifier: Programming Language :: Python :: 3.11
Classifier: Programming Language :: Python :: Implementation :: CPython
Classifier: Programming Language :: Python :: Implementation :: PyPy
Requires-Python: >=3.7.0
License-File: LICENSE
Requires-Dist: werkzeug
